README.rst
setup.py
wpadmin.py
wpadmin.egg-info/PKG-INFO
wpadmin.egg-info/SOURCES.txt
wpadmin.egg-info/dependency_links.txt
wpadmin.egg-info/entry_points.txt
wpadmin.egg-info/namespace_packages.txt
wpadmin.egg-info/not-zip-safe
wpadmin.egg-info/top_level.txt