Metadata-Version: 1.1
Name: wpadmin
Version: 0.1.0
Summary: Command line tool for WordPress
Home-page: https://github.com/raulchacon/wpadmin.py
Author: Raul J. Chacon
Author-email: raulchacon@outlook.com
License: MIT license
Keywords: wordpress admin
Platform: UNKNOWN
Classifier: Development Status :: 3 - Alpha
Classifier: Topic :: Utilities
Classifier: License :: OSI Approved :: MIT License
